mcp_ui_bridge-0.3.1.dist-info/licenses/LICENSE
mcp_ui_bridge_python/__init__.py
mcp_ui_bridge_python/main.py
mcp_ui_bridge_python/mcp_server.py
mcp_ui_bridge_python/core/__init__.py
mcp_ui_bridge_python/core/dom_parser.py
mcp_ui_bridge_python/core/playwright_controller.py
mcp_ui_bridge_python/models/__init__.py
mcp_ui_bridge_python/models/actions.py
mcp_ui_bridge_python/models/attributes.py
mcp_ui_bridge_python/models/elements.py
mcp_ui_bridge_python/models/enums.py
mcp_ui_bridge_python/models/server_options.py
mcp_ui_bridge-0.3.1.dist-info/METADATA
mcp_ui_bridge-0.3.1.dist-info/WHEEL
mcp_ui_bridge-0.3.1.dist-info/top_level.txt
mcp_ui_bridge-0.3.1.dist-info/RECORD
