Metadata-Version: 2.4
Name: mcp-ui-bridge
Version: 0.3.1
Summary: Production-ready Python MCP server for LLM-web UI automation with bulletproof pagination, robust element detection, viewport-optimized parsing and enterprise-grade stability
Author-email: Santiago Calvo <santiago@example.com>
License: MIT
Project-URL: Homepage, https://github.com/your-username/mcp-ui-bridge
Project-URL: Repository, https://github.com/your-username/mcp-ui-bridge
Project-URL: Bug Tracker, https://github.com/your-username/mcp-ui-bridge/issues
Project-URL: Documentation, https://github.com/your-username/mcp-ui-bridge#readme
Keywords: mcp,llm,automation,playwright,ui-bridge,model-context-protocol,web-automation,performance,viewport,scroll-navigation,pagination,enterprise-ready,production,stable
Classifier: Development Status :: 5 - Production/Stable
Classifier: Intended Audience :: Developers
Classifier: Programming Language :: Python :: 3
Classifier: Programming Language :: Python :: 3.8
Classifier: Programming Language :: Python :: 3.9
Classifier: Programming Language :: Python :: 3.10
Classifier: Programming Language :: Python :: 3.11
Classifier: Programming Language :: Python :: 3.12
Classifier: Topic :: Software Development :: Libraries :: Python Modules
Classifier: Topic :: Scientific/Engineering :: Artificial Intelligence
Classifier: Topic :: Internet :: WWW/HTTP :: Browsers
Classifier: Topic :: Software Development :: Testing
Requires-Python: >=3.8
License-File: LICENSE
Requires-Dist: playwright>=1.40.0
Requires-Dist: fastmcp>=2.5.0
Requires-Dist: pydantic>=2.0.0
Requires-Dist: uvicorn>=0.24.0
Requires-Dist: fastapi>=0.104.0
Provides-Extra: dev
Requires-Dist: pytest>=7.0.0; extra == "dev"
Requires-Dist: pytest-asyncio>=0.21.0; extra == "dev"
Requires-Dist: black>=23.0.0; extra == "dev"
Requires-Dist: isort>=5.12.0; extra == "dev"
Requires-Dist: mypy>=1.5.0; extra == "dev"
Dynamic: license-file
